seokit/__init__.py
seokit/__main__.py
seokit/cli.py
seokit/config.py
seokit/checklists/article-checklist.md
seokit/checklists/outline-checklist.md
seokit/checklists/seokit-checklist-template.md
seokit/commands/create-outline.md
seokit/commands/export-docx.md
seokit/commands/internal-link-list.md
seokit/commands/internal-link-sync.md
seokit/commands/internal-link.md
seokit/commands/optimize-outline.md
seokit/commands/search-intent.md
seokit/commands/seokit-init.md
seokit/commands/top-article.md
seokit/commands/write-seo.md
seokit/docs/google-eeat-quality-guidelines.md
seokit/docs/google-sqeg-appendix-rater-reference.md
seokit/scripts/config.py
seokit/scripts/docx-generator.py
seokit/scripts/internal-link-manager.py
seokit/scripts/outline-analyzer.py
seokit/scripts/perplexity_client.py
seokit/scripts/search-intent-analyzer.py
seokit/scripts/top-articles-finder.py
seokit-1.0.30.dist-info/LICENSE
seokit-1.0.30.dist-info/METADATA
seokit-1.0.30.dist-info/WHEEL
seokit-1.0.30.dist-info/entry_points.txt
seokit-1.0.30.dist-info/top_level.txt
seokit-1.0.30.dist-info/RECORD
