Metadata-Version: 2.1
Name: seokit
Version: 1.0.30
Summary: Claude Code toolkit for creating high-quality SEO articles
Author: nguyennguyenit
License: Proprietary
Project-URL: Homepage, https://github.com/nguyennguyenit/seokit
Project-URL: Documentation, https://github.com/nguyennguyenit/seokit#readme
Project-URL: Repository, https://github.com/nguyennguyenit/seokit.git
Project-URL: Issues, https://github.com/nguyennguyenit/seokit/issues
Keywords: seo,claude,ai,content,articles
Classifier: Development Status :: 4 - Beta
Classifier: Environment :: Console
Classifier: Intended Audience :: Developers
Classifier: License :: Other/Proprietary License
Classifier: Operating System :: OS Independent
Classifier: Programming Language :: Python :: 3
Classifier: Programming Language :: Python :: 3.10
Classifier: Programming Language :: Python :: 3.11
Classifier: Programming Language :: Python :: 3.12
Classifier: Topic :: Text Processing
Requires-Python: >=3.10
License-File: LICENSE
Requires-Dist: requests>=2.28.0
Requires-Dist: python-dotenv>=1.0.0
Requires-Dist: python-docx>=0.8.11
Requires-Dist: click>=8.0.0
Requires-Dist: beautifulsoup4>=4.12.0
Requires-Dist: pyyaml>=6.0.0
Requires-Dist: lxml>=5.0.0
Provides-Extra: dev
Requires-Dist: pytest>=7.0.0; extra == "dev"
Requires-Dist: pytest-cov>=4.0.0; extra == "dev"
Requires-Dist: pytest-mock>=3.12.0; extra == "dev"
Requires-Dist: responses>=0.24.0; extra == "dev"
Requires-Dist: ruff>=0.8.0; extra == "dev"
Requires-Dist: pre-commit>=3.6.0; extra == "dev"
Requires-Dist: mypy>=1.8.0; extra == "dev"
Requires-Dist: types-requests>=2.31.0; extra == "dev"
